Metadata-Version: 1.1
Name: f5-icontrol-rest
Version: 1.0.7
Summary: F5 BIG-IP iControl REST API client
Home-page: https://github.com/F5Networks/f5-icontrol-rest-python
Author: F5 Networks
Author-email: f5-icontrol-rest-python@f5.com
License: Apache License, Version 2.0
Keywords: F5,icontrol,rest,api,bigip
Platform: UNKNOWN
Classifier: Development Status :: 5 - Production/Stable
Classifier: License :: OSI Approved :: Apache Software License
Classifier: Operating System :: OS Independent
Classifier: Programming Language :: Python
Classifier: Intended Audience :: System Administrators
